{
  "cached_at": 1778903599,
  "lives": {
    "UCajbFh6e_R8QZdHAMbbi4rQ": {
      "video_id": "t2NR-6jKF6o",
      "title": "I DON'T WANNA GO INTO THE DEEP OCEAN【SUBNAUTIC | PART 3】",
      "type": "stream",
      "status": "live",
      "topic_id": "Subnautica",
      "published_at": "2026-05-15T05:41:28.000Z",
      "available_at": "2026-05-15T17:02:50.000Z",
      "start_scheduled": "2026-05-15T17:00:00.000Z",
      "start_actual": "2026-05-15T17:02:50.000Z",
      "live_viewers": 771,
      "channel": {
        "id": "UCajbFh6e_R8QZdHAMbbi4rQ",
        "name": "Crimzon Ruze Ch. HOLOSTARS-EN",
        "english_name": "Crimzon Ruze",
        "org": "Hololive",
        "suborg": "oeHOLOSTARS English -ARMIS-",
        "photo": "https://yt3.ggpht.com/oOudWIrMa-vuBgBZmxfD-ckb9F8indUDW_aoRF5Ikm2wOFitakpZITg4a7QsO5vwam_bH2xd=s800-c-k-c0x00ffffff-no-rj"
      }
    },
    "UC060r4zABV18vcahAWR1n7w": {
      "video_id": "5bT_NbBPLAs",
      "title": "Welcome to CRAYON ISLAND【TOMODACHI LIFE】",
      "type": "stream",
      "status": "live",
      "topic_id": "Tomodachi_Life",
      "published_at": "2026-05-11T03:03:02.000Z",
      "available_at": "2026-05-16T01:07:37.000Z",
      "start_scheduled": "2026-05-16T01:00:00.000Z",
      "start_actual": "2026-05-16T01:07:37.000Z",
      "live_viewers": 308,
      "channel": {
        "id": "UC060r4zABV18vcahAWR1n7w",
        "name": "Machina X Flayon Ch. HOLOSTARS-EN",
        "english_name": "Machina X Flayon",
        "org": "Hololive",
        "suborg": "ocHOLOSTARS English -TEMPUS- Vanguard",
        "photo": "https://yt3.ggpht.com/Iqey4d65X8ZWvYVCSY_xkdzdDMcw1wSESqTenq3Lk6a0nUhwPe7csjYFT5rbAhIxnUFkpQl2=s800-c-k-c0x00ffffff-no-rj"
      }
    },
    "UCMqGG8BRAiI1lJfKOpETM_w": {
      "video_id": "7o1Kw69m5Ak",
      "title": "【Resident Evil Requiem】3 - Welcome back, City of Raccoons  (Spoiler warning!)",
      "type": "stream",
      "status": "live",
      "topic_id": "residentevil",
      "published_at": "2026-05-15T15:10:10.000Z",
      "available_at": "2026-05-16T02:00:30.000Z",
      "start_scheduled": "2026-05-16T02:00:00.000Z",
      "start_actual": "2026-05-16T02:00:30.000Z",
      "live_viewers": 481,
      "channel": {
        "id": "UCMqGG8BRAiI1lJfKOpETM_w",
        "name": "Josuiji Shinri Ch. HOLOSTARS-EN",
        "english_name": "Josuiji Shinri",
        "org": "Hololive",
        "suborg": "ocHOLOSTARS English -TEMPUS- Vanguard",
        "photo": "https://yt3.ggpht.com/GkDmDWOfKfFkcVmG3-ECCRMeFR4bXlWBvuGO3xu3Ud68kVTWssXpn5q266BmtXvcHuzc5Ib2iFQ=s800-c-k-c0x00ffffff-no-rj"
      }
    },
    "UCL_qhgtOy0dy1Agp8vkySQg": {
      "video_id": "3-2TkjzFzss",
      "title": "back to streaming! talking a lot #calliolive",
      "type": "stream",
      "status": "live",
      "topic_id": "talk",
      "published_at": "2026-05-15T09:45:22.000Z",
      "available_at": "2026-05-16T02:01:02.000Z",
      "start_scheduled": "2026-05-16T02:00:00.000Z",
      "start_actual": "2026-05-16T02:01:02.000Z",
      "live_viewers": 12109,
      "channel": {
        "id": "UCL_qhgtOy0dy1Agp8vkySQg",
        "name": "Mori Calliope Ch. hololive-EN",
        "english_name": "Mori Calliope",
        "org": "Hololive",
        "suborg": "h English -Myth-",
        "photo": "https://yt3.ggpht.com/ZZuzZBS3JHrZz49K3ApCYQo1NQLhN3ApfW0R9hAaIfCLMfx5YTL51bOgJv0zk6Ikdngmmn0G=s800-c-k-c0x00ffffff-no-rj"
      }
    },
    "UCs9_O1tRPMQTHQ-N_L6FU2g": {
      "video_id": "LNCd1fRKOKc",
      "title": "【 Detroit: Become Human 】完全初見!最終回!運命を選択し、自分の未来を紡げ。【鷹嶺ルイ/ホロライブ】",
      "type": "stream",
      "status": "live",
      "topic_id": "Detroit:_Become_Human",
      "published_at": "2026-05-14T19:57:30.000Z",
      "available_at": "2026-05-16T02:01:54.000Z",
      "start_scheduled": "2026-05-16T02:00:00.000Z",
      "start_actual": "2026-05-16T02:01:54.000Z",
      "live_viewers": 6600,
      "channel": {
        "id": "UCs9_O1tRPMQTHQ-N_L6FU2g",
        "name": "Lui ch. 鷹嶺ルイ - holoX -",
        "english_name": "Takane Lui",
        "org": "Hololive",
        "suborg": "gm6th Generation -holoX-",
        "photo": "https://yt3.ggpht.com/hoR2TgfGwUZ4mbNY07Ygu88wPLY0JcArmFKZDTwaPOtJmK78gdIg3dmp87NZM8SRBCpxlv02hg=s800-c-k-c0x00ffffff-no-rj"
      }
    },
    "UCdyqAaZDKHXg4Ahi7VENThQ": {
      "video_id": "kpiN94c8On8",
      "title": "#4【ドラゴンクエストVII Reimagined】DQ7完全初見!ずっとプレイしてみたかった7の世界へ🔥【白銀ノエル/ホロライブ】※ネタバレあり",
      "type": "stream",
      "status": "live",
      "topic_id": "Dragon_Quest",
      "published_at": "2026-05-15T16:01:00.000Z",
      "available_at": "2026-05-16T02:02:24.000Z",
      "start_scheduled": "2026-05-16T02:00:00.000Z",
      "start_actual": "2026-05-16T02:02:24.000Z",
      "live_viewers": 7750,
      "channel": {
        "id": "UCdyqAaZDKHXg4Ahi7VENThQ",
        "name": "Noel Ch. 白銀ノエル",
        "english_name": "Shirogane Noel",
        "org": "Hololive",
        "suborg": "ea3rd Generation (Fantasy)",
        "photo": "https://yt3.ggpht.com/ytc/AIdro_kIKJPVEqJLs9FNMgdti5WWHtc1t0MwihOlW-ZK90nGUdk=s800-c-k-c0x00ffffff-no-rj"
      }
    },
    "UCTVSOgYuSWmNAt-lnJPkEEw": {
      "video_id": "dU0Sh4w5M6A",
      "title": "【T2 WATCHALONG】DIGITAL CIRCUS",
      "type": "stream",
      "status": "live",
      "topic_id": "membersonly",
      "published_at": "2026-05-15T15:29:59.000Z",
      "available_at": "2026-05-16T03:02:23.000Z",
      "start_scheduled": "2026-05-16T03:00:00.000Z",
      "start_actual": "2026-05-16T03:02:23.000Z",
      "live_viewers": 0,
      "channel": {
        "id": "UCTVSOgYuSWmNAt-lnJPkEEw",
        "name": "Jurard T Rexford Ch. HOLOSTARS-EN",
        "english_name": "Jurard T Rexford",
        "org": "Hololive",
        "suborg": "oeHOLOSTARS English -ARMIS-",
        "photo": "https://yt3.ggpht.com/SlCos_lnLDMWGDChJ7do9xTh4LsfXM6oKPGJqOmueHk8JMaHxxc2Y6-axY9ddMik95ATJgp5EQ=s800-c-k-c0x00ffffff-no-rj"
      }
    }
  }
}