{
  "cached_at": 1780602799,
  "lives": {
    "UCHsx4Hqa-1ORjQTh9TYDhww": {
      "video_id": "jz545PpR4uo",
      "title": "【MEMBERS ONLY】KIARAOKE!! UNARCHIVED!!! YIPPEEEEE",
      "type": "stream",
      "status": "live",
      "topic_id": "membersonly",
      "published_at": "2026-06-04T11:39:29.000Z",
      "available_at": "2026-06-04T18:01:10.000Z",
      "start_scheduled": "2026-06-04T18:00:00.000Z",
      "start_actual": "2026-06-04T18:01:10.000Z",
      "live_viewers": 0,
      "channel": {
        "id": "UCHsx4Hqa-1ORjQTh9TYDhww",
        "name": "Takanashi Kiara Ch. hololive-EN",
        "english_name": "Takanashi Kiara",
        "org": "Hololive",
        "suborg": "h English -Myth-",
        "photo": "https://yt3.ggpht.com/vnzn_RiKneABPPnp1-0SO4IAZQRXqVsL5RNDQYGR9GhT-Flm47vM4UJeyGfn4U_gteKqJMBwNA=s800-c-k-c0x00ffffff-no-rj"
      }
    }
  }
}