{
  "cached_at": 1777612941,
  "lives": {
    "UCNVEsYbiZjH5QLmGeSgTSzg": {
      "video_id": "kcfLGvuz32E",
      "title": "【 APEX 】とにかくね、時間を注げって話なんです / アステル",
      "type": "stream",
      "status": "live",
      "topic_id": "apex",
      "published_at": "2026-04-30T21:02:15.000Z",
      "available_at": "2026-04-30T22:01:35.000Z",
      "start_scheduled": "2026-04-30T22:00:00.000Z",
      "start_actual": "2026-04-30T22:01:35.000Z",
      "live_viewers": 692,
      "channel": {
        "id": "UCNVEsYbiZjH5QLmGeSgTSzg",
        "name": "astel ch.アステル",
        "english_name": "Astel Leda",
        "org": "Hololive",
        "suborg": "mcHOLOSTARS 2nd Gen (SunTempo)",
        "photo": "https://yt3.ggpht.com/dY6WTtYvc9ocqLWnyTXaGBiZSa_uIYEU7FEqGF8u3Ivbu3d3YBj2NJfls6dn_EvkvIAlr2ztfA=s800-c-k-c0x00ffffff-no-rj"
      }
    },
    "UC9p_lqQ0FEDz327Vgf5JwqA": {
      "video_id": "tZ9VnzM01xY",
      "title": "【Bayonetta 2】WITCH TIME!",
      "type": "stream",
      "status": "live",
      "topic_id": "Bayonetta",
      "published_at": "2026-04-30T14:54:06.000Z",
      "available_at": "2026-04-30T22:56:17.000Z",
      "start_scheduled": "2026-04-30T23:00:00.000Z",
      "start_actual": "2026-04-30T22:56:17.000Z",
      "live_viewers": 4651,
      "channel": {
        "id": "UC9p_lqQ0FEDz327Vgf5JwqA",
        "name": "Koseki Bijou Ch. hololive-EN",
        "english_name": "Koseki Bijou",
        "org": "Hololive",
        "suborg": "ihEnglish -Advent-",
        "photo": "https://yt3.ggpht.com/Wk5Mbh-5z_dbHTp7Hyz7OSd70Cz4GknlZOqiI2J_sIsnbm_YjWN2vb39XyrXBYj-uiMsOi-95w=s800-c-k-c0x00ffffff-no-rj"
      }
    },
    "UC060r4zABV18vcahAWR1n7w": {
      "video_id": "jQM-nTamB3E",
      "title": "【Super Smash Bros Ultimate】Pilot Fights Goo Cats Endlessly",
      "type": "stream",
      "status": "live",
      "topic_id": "smash",
      "published_at": "2026-04-20T03:01:07.000Z",
      "available_at": "2026-05-01T01:03:27.000Z",
      "start_scheduled": "2026-05-01T01:00:00.000Z",
      "start_actual": "2026-05-01T01:03:27.000Z",
      "live_viewers": 780,
      "channel": {
        "id": "UC060r4zABV18vcahAWR1n7w",
        "name": "Machina X Flayon Ch. HOLOSTARS-EN",
        "english_name": "Machina X Flayon",
        "org": "Hololive",
        "suborg": "ocHOLOSTARS English -TEMPUS- Vanguard",
        "photo": "https://yt3.ggpht.com/Iqey4d65X8ZWvYVCSY_xkdzdDMcw1wSESqTenq3Lk6a0nUhwPe7csjYFT5rbAhIxnUFkpQl2=s800-c-k-c0x00ffffff-no-rj"
      }
    },
    "UCdyqAaZDKHXg4Ahi7VENThQ": {
      "video_id": "ZM0WXIaict0",
      "title": "#10【仁王2】叫んだら終了ぐらいの喉労り精神ッッ!NO秀吉(ひできち)!!天下統一目指して脳筋パッションだ~!!!【白銀ノエル/ホロライブ】",
      "type": "stream",
      "status": "live",
      "topic_id": "Nioh",
      "published_at": "2026-04-30T01:15:55.000Z",
      "available_at": "2026-05-01T03:00:51.000Z",
      "start_scheduled": "2026-05-01T03:00:00.000Z",
      "start_actual": "2026-05-01T03:00:51.000Z",
      "live_viewers": 6286,
      "channel": {
        "id": "UCdyqAaZDKHXg4Ahi7VENThQ",
        "name": "Noel Ch. 白銀ノエル",
        "english_name": "Shirogane Noel",
        "org": "Hololive",
        "suborg": "ea3rd Generation (Fantasy)",
        "photo": "https://yt3.ggpht.com/ytc/AIdro_kIKJPVEqJLs9FNMgdti5WWHtc1t0MwihOlW-ZK90nGUdk=s800-c-k-c0x00ffffff-no-rj"
      }
    },
    "UCs9_O1tRPMQTHQ-N_L6FU2g": {
      "video_id": "QUQ7R-oS1Ac",
      "title": "【 ドラゴンボールZ KAKAROT 】完全初見!GWだ~!!!DAIMA編だ~~~~~!!!【鷹嶺ルイ/ホロライブ】※ネタバレあり",
      "type": "stream",
      "status": "live",
      "topic_id": "Dragon_Ball_Z:_Kakarot",
      "published_at": "2026-04-30T18:52:41.000Z",
      "available_at": "2026-05-01T03:02:25.000Z",
      "start_scheduled": "2026-05-01T03:00:00.000Z",
      "start_actual": "2026-05-01T03:02:25.000Z",
      "live_viewers": 5403,
      "channel": {
        "id": "UCs9_O1tRPMQTHQ-N_L6FU2g",
        "name": "Lui ch. 鷹嶺ルイ - holoX -",
        "english_name": "Takane Lui",
        "org": "Hololive",
        "suborg": "gm6th Generation -holoX-",
        "photo": "https://yt3.ggpht.com/hoR2TgfGwUZ4mbNY07Ygu88wPLY0JcArmFKZDTwaPOtJmK78gdIg3dmp87NZM8SRBCpxlv02hg=s800-c-k-c0x00ffffff-no-rj"
      }
    },
    "UCANDOlYTJT7N5jlRC3zfzVA": {
      "video_id": "Oyn9GG_IVP8",
      "title": "【P5R】初見で挑む『ペルソナ5 ザ・ロイヤル』 9日目【夕刻ロベル/ホロスターズ】※ネタバレあり",
      "type": "stream",
      "status": "live",
      "topic_id": "Persona",
      "published_at": "2026-04-30T07:58:43.000Z",
      "available_at": "2026-05-01T04:00:16.000Z",
      "start_scheduled": "2026-05-01T04:00:00.000Z",
      "start_actual": "2026-05-01T04:00:16.000Z",
      "live_viewers": 2051,
      "channel": {
        "id": "UCANDOlYTJT7N5jlRC3zfzVA",
        "name": "Roberu Ch. 夕刻ロベル",
        "english_name": "Yukoku Roberu",
        "org": "Hololive",
        "suborg": "mcHOLOSTARS 2nd Gen (SunTempo)",
        "photo": "https://yt3.ggpht.com/087yj2idU-aFOILEg1aycYQopvTOEQw4oILbI4p0u5jjSwauZRzfQkNvIhcKeUdLK-4owPQa4w=s800-c-k-c0x00ffffff-no-rj"
      }
    }
  }
}